romsearch/__init__.py
romsearch/configs/defaults.yml
romsearch/configs/regex.yml
romsearch/configs/sample_config.yml
romsearch/configs/clonelists/retool.yml
romsearch/configs/dats/no-intro.yml
romsearch/configs/dats/redump.yml
romsearch/configs/gui/rom_regex.yml
romsearch/configs/platforms/Nintendo - Game Boy Advance.yml
romsearch/configs/platforms/Nintendo - Game Boy Color.yml
romsearch/configs/platforms/Nintendo - Game Boy.yml
romsearch/configs/platforms/Nintendo - GameCube.yml
romsearch/configs/platforms/Nintendo - Nintendo 64.yml
romsearch/configs/platforms/Nintendo - Nintendo DS.yml
romsearch/configs/platforms/Nintendo - Nintendo Entertainment System.yml
romsearch/configs/platforms/Nintendo - Pokemon Mini.yml
romsearch/configs/platforms/Nintendo - Super Nintendo Entertainment System.yml
romsearch/configs/platforms/Nintendo - Virtual Boy.yml
romsearch/configs/platforms/Sega - Game Gear.yml
romsearch/configs/platforms/Sega - Mega Drive - Genesis.yml
romsearch/configs/platforms/Sony - PlayStation 2.yml
romsearch/configs/platforms/Sony - PlayStation Portable.yml
romsearch/configs/platforms/Sony - PlayStation.yml
romsearch/dev/__init__.py
romsearch/dev/gamefinder_dev.py
romsearch/dev/rahasher_dev.py
romsearch/gui/__init__.py
romsearch/gui/gui_about.py
romsearch/gui/gui_config.py
romsearch/gui/gui_rombrowser.py
romsearch/gui/gui_romsearch.py
romsearch/gui/gui_utils.py
romsearch/gui/layout_about.py
romsearch/gui/layout_about.ui
romsearch/gui/layout_romsearch.py
romsearch/gui/layout_romsearch.ui
romsearch/gui/img/logo.ico
romsearch/gui/img/logo.png
romsearch/modules/__init__.py
romsearch/modules/datmapper.py
romsearch/modules/datparser.py
romsearch/modules/dupeparser.py
romsearch/modules/gamefinder.py
romsearch/modules/rahasher.py
romsearch/modules/romchooser.py
romsearch/modules/romcleaner.py
romsearch/modules/romcompressor.py
romsearch/modules/romdownloader.py
romsearch/modules/rommover.py
romsearch/modules/romparser.py
romsearch/modules/rompatcher.py
romsearch-0.3.1.dist-info/licenses/LICENSE
romsearch-0.3.1.dist-info/METADATA
romsearch-0.3.1.dist-info/WHEEL
romsearch-0.3.1.dist-info/entry_points.txt
romsearch-0.3.1.dist-info/top_level.txt
romsearch-0.3.1.dist-info/RECORD
