Metadata-Version: 2.4
Name: romsearch
Version: 0.3.1
Summary: One Stop ROM Shop
Author: bbtufty
Maintainer: bbtufty
License:                     GNU GENERAL PUBLIC LICENSE
Project-URL: Homepage, https://github.com/bbtufty/romsearch
Project-URL: Bug Reports, https://github.com/bbtufty/romsearch/issues
Project-URL: Source, https://github.com/bbtufty/romsearch
Classifier: Development Status :: 4 - Beta
Classifier: License :: OSI Approved :: GNU General Public License v3 or later (GPLv3+)
Classifier: Programming Language :: Python
Classifier: Programming Language :: Python :: 3
Classifier: Programming Language :: Python :: 3.11
Classifier: Programming Language :: Python :: 3.12
Classifier: Programming Language :: Python :: 3 :: Only
Requires-Python: >=3.11
License-File: LICENSE
Requires-Dist: colorlog==6.9.0
Requires-Dist: discordwebhook==1.0.3
Requires-Dist: iso639-lang==2.6.0
Requires-Dist: numpy==2.2.6
Requires-Dist: packaging==25.0
Requires-Dist: pathvalidate==3.2.3
Requires-Dist: PySide6==6.9.1
Requires-Dist: pyyaml==6.0.2
Requires-Dist: wget==3.2
Requires-Dist: xmltodict==0.14.2
Provides-Extra: docs
Requires-Dist: sphinx-automodapi==0.19.0; extra == "docs"
Requires-Dist: sphinx-rtd-theme==3.0.2; extra == "docs"
Dynamic: license-file
